html_packager/__init__.py
html_packager/main.py
html_packager-0.1.7.dist-info/METADATA
html_packager-0.1.7.dist-info/WHEEL
html_packager-0.1.7.dist-info/entry_points.txt
html_packager-0.1.7.dist-info/RECORD
